tvi/solphit/discera/capability/__init__.py
tvi/solphit/discera/capability/web_search.py
tvi_solphit_discera_capability_web_search-0.5.0.dist-info/licenses/LICENSE
tvi_solphit_discera_capability_web_search-0.5.0.dist-info/METADATA
tvi_solphit_discera_capability_web_search-0.5.0.dist-info/WHEEL
tvi_solphit_discera_capability_web_search-0.5.0.dist-info/entry_points.txt
tvi_solphit_discera_capability_web_search-0.5.0.dist-info/top_level.txt
tvi_solphit_discera_capability_web_search-0.5.0.dist-info/RECORD
