Metadata-Version: 2.4
Name: tvi-solphit-discera-capability-web-search
Version: 0.5.0
Summary: Web search for a current event.
Author: Tobias Hagenbeek
License: MIT License
Project-URL: Homepage, https://github.com/SolphIT/tvi-solphit-discera-capability-web-search
Project-URL: Changelog, https://github.com/SolphIT/tvi-solphit-discera-capability-web-search/blob/main/CHANGELOG.md
Keywords: logging,argparse,utilities,jsonl,filesystem
Classifier: Programming Language :: Python :: 3
Classifier: Programming Language :: Python :: 3.12
Classifier: License :: OSI Approved :: MIT License
Classifier: Operating System :: OS Independent
Requires-Python: >=3.9
License-File: LICENSE
Requires-Dist: tvi-solphit-base>=0.2.0
Requires-Dist: ddgs>=9.9.1
Requires-Dist: httpx>=0.28.1
Requires-Dist: trafilatura>=2.0.0
Requires-Dist: tldextract>=5.3.0
Provides-Extra: test
Requires-Dist: pytest>=7.0; extra == "test"
Dynamic: license-file
